is_instance/__init__.py
is_instance-0.1.0.dist-info/METADATA
is_instance-0.1.0.dist-info/WHEEL
is_instance-0.1.0.dist-info/top_level.txt
is_instance-0.1.0.dist-info/RECORD
