Metadata-Version: 2.1
Name: is-instance
Version: 0.1.0
Summary: A better isinstance for python
Author-email: Jason Wilkes <notarealdeveloper@gmail.com>
Project-URL: source, https://github.com/notarealdeveloper/is_instance
Project-URL: download, https://pypi.org/project/is-instance/#files
